{
  "generated": "2026-06-23",
  "videos_analyzed": 355,
  "countries": 47,
  "totals": {
    "views": 253748866,
    "likes": 3296714,
    "comments": 97985
  },
  "country_attribution": "multi (b): a video is counted in every country whose search surfaced it; no per-country ranking (unreliable)",
  "top_teams": [
    {
      "team": "Japan",
      "mentions": 1846,
      "lean": "positive",
      "positive": 1805,
      "neutral": 40,
      "negative": 1
    },
    {
      "team": "Brazil",
      "mentions": 917,
      "lean": "positive",
      "positive": 617,
      "neutral": 139,
      "negative": 161
    },
    {
      "team": "Argentina",
      "mentions": 868,
      "lean": "positive",
      "positive": 699,
      "neutral": 153,
      "negative": 16
    },
    {
      "team": "South Korea",
      "mentions": 570,
      "lean": "negative",
      "positive": 4,
      "neutral": 66,
      "negative": 500
    },
    {
      "team": "Tunisia",
      "mentions": 511,
      "lean": "negative",
      "positive": 97,
      "neutral": 145,
      "negative": 269
    },
    {
      "team": "Spain",
      "mentions": 477,
      "lean": "positive",
      "positive": 394,
      "neutral": 83,
      "negative": 0
    },
    {
      "team": "Iran",
      "mentions": 354,
      "lean": "positive",
      "positive": 344,
      "neutral": 10,
      "negative": 0
    },
    {
      "team": "Turkey",
      "mentions": 335,
      "lean": "negative",
      "positive": 0,
      "neutral": 29,
      "negative": 306
    },
    {
      "team": "Egypt",
      "mentions": 306,
      "lean": "positive",
      "positive": 283,
      "neutral": 17,
      "negative": 6
    },
    {
      "team": "Saudi Arabia",
      "mentions": 274,
      "lean": "negative",
      "positive": 5,
      "neutral": 41,
      "negative": 228
    }
  ],
  "top_videos_by_views": [
    {
      "title": "Kamada scored the first goal for Japan against Tunisia. #FIFAWorldCup #FIFAWorldCupOnYT",
      "countries": [
        "AU",
        "CD",
        "CI",
        "FR",
        "GB",
        "GH",
        "HT",
        "NZ",
        "SN",
        "US"
      ],
      "reach": 10,
      "narration_en": "This post-game recap of Japan's 4-0 win over Tunisia highlights excellent teamwork and Japan's disciplined performance. Viewers across ten countries praised Kamada's goal while showing sympathy for the Tunisian team.",
      "narration_ja": "日本対チュニジアの4-0の試合結果を振り返るこの動画では、日本の素晴らしいチームワークと規律あるプレーが称賛されています。10カ国でトレンド入りし、鎌田選手のゴールへの反応やチュニジア代表への同情の声が寄せられました。",
      "views": 11645572,
      "url": "https://www.youtube.com/watch?v=TEoPhvbJ--g"
    },
    {
      "title": "Varela scores the equalizer for Cabo Verde against Uruguay. 🇺🇾 #FIFAWorldCupOnYT #shorts",
      "countries": [
        "AT",
        "CH",
        "DE"
      ],
      "reach": 3,
      "narration_en": "This highlight video of the Uruguay vs. Cabo Verde draw sparked mixed reactions regarding the underdog's performance and tactical decisions. Audience members discussed the beautiful equalizer contrasted with a notable goalkeeper blunder.",
      "narration_ja": "ウルグアイ対カーボベルデの引き分けを収めたハイライト動画で、格上の相手に対する健闘や戦術判断について議論が交わされました。美しい同点ゴールの一方で、ゴールキーパーのミスも話題となりました。",
      "views": 11244169,
      "url": "https://www.youtube.com/watch?v=LmZJpDnKqrI"
    },
    {
      "title": "Mbappé Shouldn’t Have Trusted Haaland 🤮😂 #parody #football #haaland #worldcup",
      "countries": [
        "AR",
        "CA",
        "CO",
        "EC",
        "ES",
        "JP",
        "MX",
        "PA",
        "PY",
        "TR",
        "UY",
        "UZ",
        "ZA",
        "AU",
        "GB",
        "GH",
        "NZ",
        "US"
      ],
      "reach": 18,
      "narration_en": "This surreal parody video featuring Mbappé and Haaland has trended globally in multiple languages. While many find the content entertaining, others expressed discomfort with the uncanny nature of the AI-generated imagery.",
      "narration_ja": "エムバペ選手とハーランド選手を題材にしたシュールなパロディ動画が世界中で人気です。エンターテインメントとして楽しむ声がある一方で、AI生成特有の不気味さに対する懸念も寄せられています。",
      "views": 5956697,
      "url": "https://www.youtube.com/watch?v=khhvTOHXsEk"
    },
    {
      "title": "予言者 本田圭佑 / 2026 FIFA ワールドカップ 日本 vs チュニジア【本田圭佑解説】",
      "countries": [
        "JP"
      ],
      "reach": 1,
      "narration_en": "Keisuke Honda's insightful commentary on Japan's victory over Tunisia is a hit in Japan, with fans praising his accurate match predictions. The discussion highlights his entertaining style and focus on players like Ayase Ueda.",
      "narration_ja": "日本対チュニジア戦を解説した本田圭佑氏の動画が、日本国内で高い注目を集めています。的中する予言や本田氏のエンターテインメント性、上田綺世選手らへの敬意が視聴者から高く評価されています。",
      "views": 5749138,
      "url": "https://www.youtube.com/watch?v=rcBiZBon6KY"
    },
    {
      "title": "I Hid $1,000 at a World Cup Match",
      "countries": [
        "CI",
        "SN"
      ],
      "reach": 2,
      "narration_en": "A creator's attempt to hide $1,000 at a World Cup match stirred debate among French-speaking viewers. Opinions vary from envy of the lucky fan to criticism regarding the ethics of the video's content.",
      "narration_ja": "ワールドカップの試合会場に1000ドルを隠すという企画動画に対し、フランス語圏の視聴者の間で議論が巻き起こりました。ファンが幸運を羨む一方で、動画の内容や倫理性に対する批判的な意見も見られます。",
      "views": 5593313,
      "url": "https://www.youtube.com/watch?v=ub6fzBj-5sQ"
    },
    {
      "title": "イケイケどんどんやて！これ！2026 FIFA ワールドカップ 日本 vs チュニジア 【本田圭佑解説】",
      "countries": [
        "JP"
      ],
      "reach": 1,
      "narration_en": "Keisuke Honda's commentary on Japan's win over Tunisia resonated with fans, specifically his 'Ike-ike Dondon' catchphrase. Viewers feel his engaging analysis makes the match much more enjoyable to watch.",
      "narration_ja": "日本対チュニジア戦における本田圭佑氏の解説動画で、「イケイケどんどん」というフレーズが視聴者の間で話題となりました。本田氏の率直な解説が、サッカー観戦をより楽しいものにしていると好評です。",
      "views": 5141411,
      "url": "https://www.youtube.com/watch?v=KO_HCw70_iE"
    },
    {
      "title": "Argentina vs. Austria Pre-Game + First 10 Minutes | FIFA World Cup",
      "countries": [
        "AR",
        "AT",
        "AU",
        "BA",
        "BE",
        "BR",
        "CA",
        "CD",
        "CH",
        "CI",
        "CO",
        "CV",
        "CW",
        "CZ",
        "DE",
        "EC",
        "ES",
        "FR",
        "GB",
        "GH",
        "HR",
        "HT",
        "IR",
        "JP",
        "KR",
        "MX",
        "NL",
        "NO",
        "NZ",
        "PA",
        "PT",
        "PY",
        "SE",
        "SN",
        "TR",
        "US",
        "UY",
        "UZ",
        "ZA"
      ],
      "reach": 39,
      "narration_en": "This pre-game coverage of Argentina vs. Austria features intense debate surrounding Messi's legacy. Across many countries, fans are actively discussing his performance and recent refereeing decisions.",
      "narration_ja": "アルゼンチン対オーストリアの試合前プレビュー動画では、メッシ選手の功績を巡る熱い議論が繰り広げられています。多くの国から視聴者が集まり、プレー内容や判定に対する意見が交わされました。",
      "views": 4735163,
      "url": "https://www.youtube.com/watch?v=iCms_mGMeZ0"
    },
    {
      "title": "Can I Start a Wave at the FIFA World Cup? 🌊⚽️🏆 #ad #FIFAWorldCup",
      "countries": [
        "BA",
        "HR",
        "SE"
      ],
      "reach": 3,
      "narration_en": "This vlog shows a fan attempting to start a stadium wave at a match, sparking divided feedback. While some admire the persistence and appearance, others criticized the filming style over watching the game.",
      "narration_ja": "スタジアムでウェーブを起こそうとするファンを捉えた動画に対し、様々な反応が集まっています。粘り強い姿勢を称賛する声がある一方、試合観戦よりも撮影を優先する姿勢に批判的な意見も寄せられました。",
      "views": 4664474,
      "url": "https://www.youtube.com/watch?v=kxIyC-vj-lU"
    },
    {
      "title": "Curaçao’s defense stops Ecuador attempts. #FIFAWorldCupOnYT",
      "countries": [
        "AT",
        "CH",
        "DE",
        "AU",
        "CD",
        "GB",
        "GH",
        "HT",
        "NZ",
        "SN",
        "US",
        "CI",
        "FR"
      ],
      "reach": 13,
      "narration_en": "Curaçao's resilient defensive performance against Ecuador captured global attention. Viewers praised the incredible goalkeeping while expressing disappointment in the goalless result and refereeing decisions.",
      "narration_ja": "エクアドルを相手に堅守を見せたキュラソー代表の戦いぶりに、世界中から注目が集まりました。素晴らしいセーブを見せたゴールキーパーへの称賛の声の一方で、無得点の結果や判定に対する不満も聞かれました。",
      "views": 4313549,
      "url": "https://www.youtube.com/watch?v=4RocbKM5Ozs"
    },
    {
      "title": "Zlatan Ibrahimovic in training😂😂😂#football #soccer #zlatan",
      "countries": [
        "AU",
        "CD",
        "GB",
        "GH",
        "HT",
        "NZ",
        "SN",
        "US",
        "CI",
        "FR"
      ],
      "reach": 10,
      "narration_en": "Fans are enjoying this training clip of Zlatan Ibrahimović, highlighting his legendary charisma and incredible shot power. The content has trended in several countries with audiences appreciating his unique technique.",
      "narration_ja": "ズラタン・イブラヒモビッチ選手のトレーニング風景を収めたこの動画は、彼の伝説的なカリスマ性と驚異的なシュート力で人気です。その独特な技術と個性が、多くの視聴者を魅了しています。",
      "views": 3479279,
      "url": "https://www.youtube.com/watch?v=-E9I2R6CduA"
    }
  ],
  "top_videos_by_reach": [
    {
      "title": "Argentina vs. Austria Pre-Game + First 10 Minutes | FIFA World Cup",
      "countries": [
        "AR",
        "AT",
        "AU",
        "BA",
        "BE",
        "BR",
        "CA",
        "CD",
        "CH",
        "CI",
        "CO",
        "CV",
        "CW",
        "CZ",
        "DE",
        "EC",
        "ES",
        "FR",
        "GB",
        "GH",
        "HR",
        "HT",
        "IR",
        "JP",
        "KR",
        "MX",
        "NL",
        "NO",
        "NZ",
        "PA",
        "PT",
        "PY",
        "SE",
        "SN",
        "TR",
        "US",
        "UY",
        "UZ",
        "ZA"
      ],
      "reach": 39,
      "narration_en": "This pre-game coverage of Argentina vs. Austria features intense debate surrounding Messi's legacy. Across many countries, fans are actively discussing his performance and recent refereeing decisions.",
      "narration_ja": "アルゼンチン対オーストリアの試合前プレビュー動画では、メッシ選手の功績を巡る熱い議論が繰り広げられています。多くの国から視聴者が集まり、プレー内容や判定に対する意見が交わされました。",
      "views": 4735163,
      "url": "https://www.youtube.com/watch?v=iCms_mGMeZ0"
    },
    {
      "title": "Vinicius Celebrating Like Ronaldo At 2026 FIFA World Cup Match☠️🥶 #football #soccer #short",
      "countries": [
        "BA",
        "BR",
        "KR",
        "PT",
        "UZ",
        "IR",
        "CA",
        "CV",
        "NO",
        "PY",
        "BE",
        "CW",
        "NL",
        "ZA",
        "CZ",
        "MX",
        "ES",
        "HR",
        "AR",
        "AT",
        "CH",
        "CO",
        "EC",
        "PA",
        "SE",
        "UY",
        "DE",
        "AU",
        "GB",
        "NZ",
        "GH",
        "US"
      ],
      "reach": 32,
      "narration_en": "",
      "narration_ja": "",
      "views": 596153,
      "url": "https://www.youtube.com/watch?v=kAzS2R8_GdY"
    },
    {
      "title": "Highlights | Tunisia 0-4 Japan | FIFA World Cup 2026™",
      "countries": [
        "BR",
        "PT",
        "TR",
        "IR",
        "KR",
        "UZ",
        "BE",
        "CV",
        "CW",
        "NL",
        "CZ",
        "NO",
        "HR",
        "SE",
        "CO",
        "EC",
        "ES",
        "PA",
        "PY",
        "UY",
        "AR",
        "MX",
        "CH",
        "JP",
        "AT",
        "DE",
        "CI",
        "FR",
        "HT",
        "CD",
        "SN"
      ],
      "reach": 31,
      "narration_en": "",
      "narration_ja": "",
      "views": 1205587,
      "url": "https://www.youtube.com/watch?v=V7z6uzD91Ao"
    },
    {
      "title": "Highlights | Netherlands 5-1 Sweden | FIFA World Cup 2026™",
      "countries": [
        "BR",
        "PT",
        "TR",
        "IR",
        "KR",
        "UZ",
        "BE",
        "CV",
        "CW",
        "NL",
        "CZ",
        "NO",
        "HR",
        "SE",
        "CO",
        "EC",
        "ES",
        "PA",
        "PY",
        "UY",
        "AR",
        "MX",
        "CH",
        "JP",
        "AT",
        "DE",
        "CI",
        "FR",
        "HT",
        "CD",
        "SN"
      ],
      "reach": 31,
      "narration_en": "",
      "narration_ja": "",
      "views": 831423,
      "url": "https://www.youtube.com/watch?v=tm1PRvtp1PM"
    },
    {
      "title": "Highlights | Germany 2-1 Cote d'Ivoire | FIFA World Cup 2026™",
      "countries": [
        "BR",
        "PT",
        "TR",
        "IR",
        "KR",
        "UZ",
        "BE",
        "CV",
        "CW",
        "NL",
        "CZ",
        "NO",
        "HR",
        "SE",
        "CO",
        "EC",
        "ES",
        "PA",
        "PY",
        "UY",
        "AR",
        "MX",
        "JP",
        "CH",
        "AT",
        "DE",
        "CI",
        "FR",
        "CD",
        "SN"
      ],
      "reach": 30,
      "narration_en": "",
      "narration_ja": "",
      "views": 868216,
      "url": "https://www.youtube.com/watch?v=_3PYS5oCgvQ"
    },
    {
      "title": "[PES 2021] Argentina vs Austria. Video Game Simulation - World Cup 2026 Full Match PES 2021",
      "countries": [
        "BE",
        "BR",
        "CV",
        "CW",
        "CZ",
        "IR",
        "KR",
        "NL",
        "NO",
        "PT",
        "AT",
        "CH",
        "CO",
        "DE",
        "EC",
        "ES",
        "HR",
        "MX",
        "PA",
        "PY",
        "SE",
        "TR",
        "UY",
        "UZ",
        "AR",
        "CI",
        "JP"
      ],
      "reach": 27,
      "narration_en": "",
      "narration_ja": "",
      "views": 1978112,
      "url": "https://www.youtube.com/watch?v=0lkF8Gy1CCc"
    },
    {
      "title": "LIVE WATCHALONG | Spain vs Saudi Arabia | FIFA World Cup 2026 | SportyTV",
      "countries": [
        "BA",
        "TR",
        "UZ",
        "BR",
        "KR",
        "PT",
        "IR",
        "CV",
        "NO",
        "PY",
        "BE",
        "CW",
        "NL",
        "CZ",
        "MX",
        "ES",
        "HR",
        "AR",
        "CO",
        "EC",
        "PA",
        "SE",
        "UY",
        "AT",
        "CH",
        "DE",
        "JP"
      ],
      "reach": 27,
      "narration_en": "",
      "narration_ja": "",
      "views": 347797,
      "url": "https://www.youtube.com/watch?v=ya4ozLeQxyo"
    },
    {
      "title": "🔴LIVE - ARGENTINA vs AUSTRIA | FIFA World Cup 2026 | PES 21 Football Simulation Gameplay",
      "countries": [
        "BR",
        "CV",
        "PT",
        "KR",
        "TR",
        "CO",
        "EC",
        "ES",
        "IR",
        "PA",
        "PY",
        "UY",
        "UZ",
        "AR",
        "BE",
        "CW",
        "MX",
        "NL",
        "CZ",
        "NO",
        "HR",
        "SE",
        "AT",
        "CH",
        "DE",
        "JP"
      ],
      "reach": 26,
      "narration_en": "",
      "narration_ja": "",
      "views": 1033251,
      "url": "https://www.youtube.com/watch?v=0ExfG4SZVao"
    },
    {
      "title": "🔴LIVE - ARGENTINA vs AUSTRIA | FIFA World Cup 2026 | Group- J | PES 21 Simulation",
      "countries": [
        "BR",
        "PT",
        "IR",
        "BE",
        "CV",
        "CW",
        "KR",
        "NL",
        "TR",
        "UZ",
        "CZ",
        "NO",
        "HR",
        "PY",
        "SE",
        "ES",
        "MX",
        "AR",
        "CO",
        "EC",
        "PA",
        "UY",
        "CH",
        "AT",
        "DE",
        "JP"
      ],
      "reach": 26,
      "narration_en": "",
      "narration_ja": "",
      "views": 678797,
      "url": "https://www.youtube.com/watch?v=ctp0xJUyCuM"
    },
    {
      "title": "New Zealand vs Egypt | FIFA World Cup - Round 2 - 2026 | PES 21 Video Game - Simulation",
      "countries": [
        "BR",
        "PT",
        "IR",
        "KR",
        "TR",
        "UZ",
        "BE",
        "CW",
        "NL",
        "CV",
        "CZ",
        "NO",
        "HR",
        "PY",
        "SE",
        "ES",
        "MX",
        "CO",
        "EC",
        "PA",
        "UY",
        "AR",
        "CH",
        "AT",
        "DE",
        "JP"
      ],
      "reach": 26,
      "narration_en": "",
      "narration_ja": "",
      "views": 505522,
      "url": "https://www.youtube.com/watch?v=08APav0p6CQ"
    }
  ],
  "sentiment_avg": {
    "positive": 51.4112676056338,
    "negative": 19.864788732394366,
    "neutral": 28.72394366197183
  },
  "comments_analyzed": 18563,
  "top_positive_themes": [
    {
      "theme_en": "Keisuke Honda's commentary is entertaining",
      "theme_ja": "本田圭佑の解説が面白い",
      "mentions": 205
    },
    {
      "theme_en": "Support for Spain national team",
      "theme_ja": "スペイン代表への応援",
      "mentions": 181
    },
    {
      "theme_en": "Support for Cristiano Ronaldo",
      "theme_ja": "クリスティアーノ・ロナウドへの支持",
      "mentions": 115
    },
    {
      "theme_en": "High quality editing",
      "theme_ja": "編集技術の高さ",
      "mentions": 104
    },
    {
      "theme_en": "Support for Brazil national team",
      "theme_ja": "ブラジル代表への応援",
      "mentions": 88
    },
    {
      "theme_en": "Congratulations on Egypt's victory",
      "theme_ja": "エジプトの勝利への祝福",
      "mentions": 85
    },
    {
      "theme_en": "Congratulations on Egypt's historic win",
      "theme_ja": "エジプト代表の歴史的勝利への祝福",
      "mentions": 85
    },
    {
      "theme_en": "Enthusiastic support for players",
      "theme_ja": "選手への熱狂的な応援",
      "mentions": 85
    }
  ],
  "top_negative_themes": [
    {
      "theme_en": "Criticism of Ochoa (lack of skill, media hype)",
      "theme_ja": "オチョアへの批判（実力不足・メディアの過大評価）",
      "mentions": 65
    },
    {
      "theme_en": "Distrust in the head coach (Hong Myung-bo)",
      "theme_ja": "監督（洪明甫）への不信感",
      "mentions": 65
    },
    {
      "theme_en": "Skepticism about who started the wave",
      "theme_ja": "ウェーブの真偽に対する疑念",
      "mentions": 65
    },
    {
      "theme_en": "Unfairness regarding Messi's red card decision",
      "theme_ja": "メッシへのレッドカード判定の不公平さ",
      "mentions": 65
    },
    {
      "theme_en": "Corruption and cronyism within the KFA",
      "theme_ja": "サッカー協会（KFA）の腐敗と癒着",
      "mentions": 65
    },
    {
      "theme_en": "Mourning Oliver Tree's death",
      "theme_ja": "オリバー・ツリーの訃報への追悼",
      "mentions": 65
    },
    {
      "theme_en": "Exorbitant ticket prices",
      "theme_ja": "チケット価格の高騰",
      "mentions": 65
    },
    {
      "theme_en": "Sadness from match defeat",
      "theme_ja": "試合の敗北による悲しみ",
      "mentions": 65
    }
  ]
}