{
  "generated": "2026-07-14",
  "videos_analyzed": 282,
  "countries": 47,
  "totals": {
    "views": 375582368,
    "likes": 4559121,
    "comments": 187279
  },
  "country_attribution": "multi (b): a video is counted in every country whose search surfaced it; no per-country ranking (unreliable)",
  "top_teams": [
    {
      "team": "Argentina",
      "mentions": 3187,
      "lean": "positive",
      "positive": 1947,
      "neutral": 423,
      "negative": 817
    },
    {
      "team": "England",
      "mentions": 1018,
      "lean": "positive",
      "positive": 421,
      "neutral": 431,
      "negative": 166
    },
    {
      "team": "Switzerland",
      "mentions": 911,
      "lean": "negative",
      "positive": 73,
      "neutral": 405,
      "negative": 433
    },
    {
      "team": "Norway",
      "mentions": 702,
      "lean": "positive",
      "positive": 386,
      "neutral": 120,
      "negative": 196
    },
    {
      "team": "France",
      "mentions": 359,
      "lean": "positive",
      "positive": 90,
      "neutral": 230,
      "negative": 39
    },
    {
      "team": "Brazil",
      "mentions": 320,
      "lean": "negative",
      "positive": 105,
      "neutral": 96,
      "negative": 119
    },
    {
      "team": "Spain",
      "mentions": 279,
      "lean": "positive",
      "positive": 175,
      "neutral": 98,
      "negative": 6
    },
    {
      "team": "Portugal",
      "mentions": 182,
      "lean": "negative",
      "positive": 57,
      "neutral": 63,
      "negative": 62
    },
    {
      "team": "Egypt",
      "mentions": 147,
      "lean": "positive",
      "positive": 97,
      "neutral": 41,
      "negative": 9
    },
    {
      "team": "Algeria",
      "mentions": 105,
      "lean": "negative",
      "positive": 38,
      "neutral": 7,
      "negative": 60
    }
  ],
  "top_videos_by_views": [
    {
      "title": "Julián Álvarez scores the comeback goal for Argentina against Switzerland. #FIFAWorldCupOnYT",
      "countries": [
        "DE"
      ],
      "reach": 1,
      "narration_en": "",
      "narration_ja": "",
      "views": 45085831,
      "url": "https://www.youtube.com/watch?v=K6RxEu9CLGc"
    },
    {
      "title": "Argentina 🇦🇷 Vs Switzerland 🇨🇭 | 2026 FIFA World Cup",
      "countries": [
        "AR",
        "AT",
        "BA",
        "BE",
        "BR",
        "CA",
        "CH",
        "CO",
        "CV",
        "CW",
        "CZ",
        "DE",
        "EC",
        "ES",
        "GB",
        "HR",
        "IR",
        "JP",
        "KR",
        "MX",
        "NL",
        "NO",
        "PA",
        "PT",
        "PY",
        "SE",
        "TR",
        "US",
        "UY",
        "UZ",
        "ZA",
        "AU",
        "CD",
        "CI",
        "FR",
        "GH",
        "NZ",
        "SN",
        "HT"
      ],
      "reach": 39,
      "narration_en": "",
      "narration_ja": "",
      "views": 16829450,
      "url": "https://www.youtube.com/watch?v=wPrN4ELa4HY"
    },
    {
      "title": "Ronaldo vs Messi: Football IQ Test 🧠⚡ Who Sees More? #football #shorts",
      "countries": [
        "HT"
      ],
      "reach": 1,
      "narration_en": "",
      "narration_ja": "",
      "views": 15576416,
      "url": "https://www.youtube.com/watch?v=K_O7xOuLaRI"
    },
    {
      "title": "Argentina 🆚 Switzerland #FIFAWorldCupOnYT",
      "countries": [
        "UZ",
        "BA",
        "BE",
        "CW",
        "CZ",
        "DE",
        "HR",
        "IR",
        "JP",
        "KR",
        "NL",
        "NO",
        "SE"
      ],
      "reach": 13,
      "narration_en": "",
      "narration_ja": "",
      "views": 13143692,
      "url": "https://www.youtube.com/watch?v=SQ8kjqCPSf4"
    },
    {
      "title": "Ronaldo vs Messi: Pure Entertainment 🍿🔥 Who Made Football Fun? #football #shorts",
      "countries": [
        "AU",
        "CD",
        "CI",
        "FR",
        "GH",
        "NZ",
        "SN",
        "HT"
      ],
      "reach": 8,
      "narration_en": "",
      "narration_ja": "",
      "views": 13069894,
      "url": "https://www.youtube.com/watch?v=hSQhE-jVj4A"
    },
    {
      "title": "THANK YOU, RONALDO🥹🇵🇹",
      "countries": [
        "EC",
        "PY",
        "UZ",
        "CO",
        "PA",
        "TR",
        "UY",
        "AR",
        "ES",
        "MX"
      ],
      "reach": 10,
      "narration_en": "",
      "narration_ja": "",
      "views": 8382633,
      "url": "https://www.youtube.com/watch?v=0rG_uyO8p10"
    },
    {
      "title": "ملخص مباراة الأرجنتين وسويسرا  | الدور ربع النهائي - كأس العالم FIFA 2026™",
      "countries": [
        "DZ",
        "EG",
        "IQ",
        "JO",
        "MA",
        "QA",
        "SA",
        "TN"
      ],
      "reach": 8,
      "narration_en": "",
      "narration_ja": "",
      "views": 7936236,
      "url": "https://www.youtube.com/watch?v=7c-BwSVALZM"
    },
    {
      "title": "Lautaro Martínez seals Argentina win against Switzerland for the Quarter-finals. #FIFAWorldCupOnYT",
      "countries": [
        "DE"
      ],
      "reach": 1,
      "narration_en": "",
      "narration_ja": "",
      "views": 6488332,
      "url": "https://www.youtube.com/watch?v=6AuLLxVQ9Vo"
    },
    {
      "title": "I Surprised Haaland with a Custom Jacket",
      "countries": [
        "GB",
        "US",
        "CA",
        "ZA",
        "AU",
        "CD",
        "CI",
        "GH",
        "NZ",
        "SN",
        "FR",
        "HT"
      ],
      "reach": 12,
      "narration_en": "",
      "narration_ja": "",
      "views": 6470591,
      "url": "https://www.youtube.com/watch?v=i4Fld5vnfL8"
    },
    {
      "title": "eFootball PES 21 Gameplay | World Cup 2026 Live Simulation",
      "countries": [
        "AR",
        "AT",
        "BA",
        "BE",
        "BR",
        "CA",
        "CH",
        "CO",
        "CV",
        "CW",
        "CZ",
        "EC",
        "ES",
        "GB",
        "HR",
        "IR",
        "JP",
        "KR",
        "MX",
        "NL",
        "NO",
        "PA",
        "PT",
        "PY",
        "SE",
        "TR",
        "US",
        "UY",
        "ZA",
        "AU",
        "CD",
        "CI",
        "FR",
        "GH",
        "NZ",
        "SN",
        "HT"
      ],
      "reach": 37,
      "narration_en": "",
      "narration_ja": "",
      "views": 6212652,
      "url": "https://www.youtube.com/watch?v=ASVmf2QuE3I"
    }
  ],
  "top_videos_by_reach": [
    {
      "title": "Argentina 🇦🇷 Vs Switzerland 🇨🇭 | 2026 FIFA World Cup",
      "countries": [
        "AR",
        "AT",
        "BA",
        "BE",
        "BR",
        "CA",
        "CH",
        "CO",
        "CV",
        "CW",
        "CZ",
        "DE",
        "EC",
        "ES",
        "GB",
        "HR",
        "IR",
        "JP",
        "KR",
        "MX",
        "NL",
        "NO",
        "PA",
        "PT",
        "PY",
        "SE",
        "TR",
        "US",
        "UY",
        "UZ",
        "ZA",
        "AU",
        "CD",
        "CI",
        "FR",
        "GH",
        "NZ",
        "SN",
        "HT"
      ],
      "reach": 39,
      "narration_en": "",
      "narration_ja": "",
      "views": 16829450,
      "url": "https://www.youtube.com/watch?v=wPrN4ELa4HY"
    },
    {
      "title": "FIFA World Cup Semi Final 1☠️🗿",
      "countries": [
        "BR",
        "PT",
        "AT",
        "CV",
        "DE",
        "HR",
        "CH",
        "CO",
        "EC",
        "KR",
        "PA",
        "PY",
        "UY",
        "AR",
        "CZ",
        "ES",
        "IR",
        "MX",
        "NO",
        "TR",
        "BE",
        "CW",
        "GB",
        "JP",
        "NL",
        "SE",
        "BA",
        "CA",
        "CD",
        "CI",
        "SN",
        "US",
        "AU",
        "FR",
        "HT",
        "NZ",
        "ZA",
        "GH"
      ],
      "reach": 38,
      "narration_en": "",
      "narration_ja": "",
      "views": 2782107,
      "url": "https://www.youtube.com/watch?v=NNxIfWQTr-I"
    },
    {
      "title": "Julián Alvarez Goal | Argentina 3-1 Switzerland | FIFA World Cup 2026™",
      "countries": [
        "BR",
        "PT",
        "CV",
        "DE",
        "HR",
        "CH",
        "AT",
        "CZ",
        "IR",
        "KR",
        "NO",
        "BE",
        "CO",
        "CW",
        "EC",
        "GB",
        "JP",
        "PA",
        "PY",
        "SE",
        "TR",
        "UY",
        "AR",
        "BA",
        "CD",
        "FR",
        "MX",
        "NL",
        "CI",
        "SN",
        "ES",
        "US",
        "AU",
        "CA",
        "GH",
        "HT",
        "ZA",
        "NZ"
      ],
      "reach": 38,
      "narration_en": "",
      "narration_ja": "",
      "views": 467213,
      "url": "https://www.youtube.com/watch?v=qY5SdQa7-jA"
    },
    {
      "title": "🔴LIVE  Argentina vs Switzerland | FIFA World Cup 2026 I Full Match Streaming | Video Game Simulation",
      "countries": [
        "DE",
        "UZ",
        "BR",
        "PT",
        "CV",
        "HR",
        "CH",
        "AT",
        "GB",
        "TR",
        "CD",
        "CO",
        "FR",
        "PA",
        "PY",
        "UY",
        "AR",
        "EC",
        "MX",
        "CI",
        "CZ",
        "KR",
        "NO",
        "SN",
        "ES",
        "IR",
        "JP",
        "BE",
        "SE",
        "BA",
        "CW",
        "NL",
        "CA",
        "HT",
        "AU",
        "GH",
        "ZA",
        "NZ"
      ],
      "reach": 38,
      "narration_en": "",
      "narration_ja": "",
      "views": 294518,
      "url": "https://www.youtube.com/watch?v=5EH2PJggWkM"
    },
    {
      "title": "eFootball PES 21 Gameplay | World Cup 2026 Live Simulation",
      "countries": [
        "AR",
        "AT",
        "BA",
        "BE",
        "BR",
        "CA",
        "CH",
        "CO",
        "CV",
        "CW",
        "CZ",
        "EC",
        "ES",
        "GB",
        "HR",
        "IR",
        "JP",
        "KR",
        "MX",
        "NL",
        "NO",
        "PA",
        "PT",
        "PY",
        "SE",
        "TR",
        "US",
        "UY",
        "ZA",
        "AU",
        "CD",
        "CI",
        "FR",
        "GH",
        "NZ",
        "SN",
        "HT"
      ],
      "reach": 37,
      "narration_en": "",
      "narration_ja": "",
      "views": 6212652,
      "url": "https://www.youtube.com/watch?v=ASVmf2QuE3I"
    },
    {
      "title": "Argentina vs Switzerland | FIFA World Cup 2026 I Full Match Streaming | VideoGame Simulation",
      "countries": [
        "BR",
        "CV",
        "GB",
        "PT",
        "US",
        "AT",
        "CA",
        "CO",
        "PA",
        "TR",
        "UY",
        "ZA",
        "AR",
        "AU",
        "BE",
        "CD",
        "CH",
        "CI",
        "CW",
        "CZ",
        "EC",
        "ES",
        "GH",
        "HR",
        "IR",
        "KR",
        "MX",
        "NL",
        "NO",
        "NZ",
        "PY",
        "SE",
        "SN",
        "BA",
        "FR",
        "HT",
        "JP"
      ],
      "reach": 37,
      "narration_en": "",
      "narration_ja": "",
      "views": 3402636,
      "url": "https://www.youtube.com/watch?v=OP_ZcRKORP0"
    },
    {
      "title": "Fifa WORLD CUP 2026 SHOCK! Only 4 Teams Remain… Who Will Become World Champion?#FIFAWorldCup2026",
      "countries": [
        "BR",
        "PT",
        "CV",
        "AT",
        "HR",
        "TR",
        "CH",
        "GB",
        "KR",
        "CA",
        "CD",
        "CI",
        "CO",
        "CZ",
        "IR",
        "NO",
        "PA",
        "SN",
        "US",
        "UY",
        "AR",
        "AU",
        "BE",
        "CW",
        "EC",
        "ES",
        "FR",
        "HT",
        "JP",
        "MX",
        "NL",
        "NZ",
        "PY",
        "SE",
        "ZA",
        "BA",
        "GH"
      ],
      "reach": 37,
      "narration_en": "",
      "narration_ja": "",
      "views": 1280363,
      "url": "https://www.youtube.com/watch?v=DofW6pk5ncw"
    },
    {
      "title": "Highlights | Norway 1-2 England | FIFA World Cup 2026™",
      "countries": [
        "BR",
        "PT",
        "CV",
        "DE",
        "AT",
        "CH",
        "GB",
        "KR",
        "TR",
        "PA",
        "UY",
        "BE",
        "CA",
        "CD",
        "CO",
        "CZ",
        "EC",
        "ES",
        "FR",
        "IR",
        "JP",
        "MX",
        "NO",
        "PY",
        "SE",
        "SN",
        "US",
        "AR",
        "AU",
        "BA",
        "CI",
        "CW",
        "GH",
        "NL",
        "NZ",
        "ZA",
        "HT"
      ],
      "reach": 37,
      "narration_en": "",
      "narration_ja": "",
      "views": 1268831,
      "url": "https://www.youtube.com/watch?v=PnFUiq8m9os"
    },
    {
      "title": "World Cup 2026 Day 31",
      "countries": [
        "BR",
        "PT",
        "CV",
        "HR",
        "CH",
        "AT",
        "CO",
        "CZ",
        "EC",
        "NO",
        "PA",
        "PY",
        "UY",
        "AR",
        "GB",
        "IR",
        "KR",
        "MX",
        "TR",
        "BE",
        "CW",
        "SE",
        "BA",
        "CD",
        "ES",
        "FR",
        "JP",
        "NL",
        "CI",
        "SN",
        "US",
        "CA",
        "HT",
        "AU",
        "GH",
        "ZA",
        "NZ"
      ],
      "reach": 37,
      "narration_en": "",
      "narration_ja": "",
      "views": 697606,
      "url": "https://www.youtube.com/watch?v=DB2L7fi6MtA"
    },
    {
      "title": "Argentina vs Switzerland World Cup 2026 WATCHALONG LIVESTREAM",
      "countries": [
        "BR",
        "PT",
        "CV",
        "HR",
        "CH",
        "AT",
        "CO",
        "CZ",
        "EC",
        "GB",
        "NO",
        "PA",
        "PY",
        "UY",
        "AR",
        "IR",
        "KR",
        "MX",
        "TR",
        "BE",
        "CW",
        "SE",
        "BA",
        "CD",
        "ES",
        "FR",
        "JP",
        "NL",
        "CI",
        "SN",
        "US",
        "CA",
        "HT",
        "AU",
        "GH",
        "ZA",
        "NZ"
      ],
      "reach": 37,
      "narration_en": "",
      "narration_ja": "",
      "views": 410662,
      "url": "https://www.youtube.com/watch?v=y1hJOg6ektU"
    }
  ],
  "sentiment_avg": {
    "positive": 42.833333333333336,
    "negative": 26.03900709219858,
    "neutral": 31.127659574468087
  },
  "comments_analyzed": 15624,
  "top_positive_themes": [
    {
      "theme_en": "Praise for Messi",
      "theme_ja": "メッシへの称賛",
      "mentions": 168
    },
    {
      "theme_en": "Argentina's victory",
      "theme_ja": "アルゼンチンの勝利",
      "mentions": 150
    },
    {
      "theme_en": "Support for Argentina",
      "theme_ja": "アルゼンチン代表への応援",
      "mentions": 122
    },
    {
      "theme_en": "Praise for Argentina's victory",
      "theme_ja": "アルゼンチンの勝利への称賛",
      "mentions": 113
    },
    {
      "theme_en": "Support for specific players",
      "theme_ja": "特定の選手への支持",
      "mentions": 110
    },
    {
      "theme_en": "Support for Argentina national team",
      "theme_ja": "アルゼンチン代表への応援",
      "mentions": 96
    },
    {
      "theme_en": "Argentina's victory and strength",
      "theme_ja": "アルゼンチンの勝利と強さ",
      "mentions": 95
    },
    {
      "theme_en": "Humor and laughter",
      "theme_ja": "ユーモアと笑い",
      "mentions": 91
    }
  ],
  "top_negative_themes": [
    {
      "theme_en": "Dissatisfaction with refereeing",
      "theme_ja": "審判の判定への不満",
      "mentions": 189
    },
    {
      "theme_en": "Embolo's dive",
      "theme_ja": "エンボロのシミュレーション",
      "mentions": 132
    },
    {
      "theme_en": "Sadness over retirement and end of an era",
      "theme_ja": "引退や時代の終わりに対する悲しみ",
      "mentions": 120
    },
    {
      "theme_en": "FIFA corruption and fraud allegations",
      "theme_ja": "FIFAの腐敗と不正疑惑",
      "mentions": 110
    },
    {
      "theme_en": "Frustration with referee decisions",
      "theme_ja": "審判の判定への不満",
      "mentions": 81
    },
    {
      "theme_en": "Player simulation/diving",
      "theme_ja": "選手のシミュレーション行為",
      "mentions": 80
    },
    {
      "theme_en": "Mourning the death of a player",
      "theme_ja": "選手の訃報への追悼",
      "mentions": 80
    },
    {
      "theme_en": "Sadness about the tournament ending",
      "theme_ja": "大会が終わることへの寂しさ",
      "mentions": 72
    }
  ]
}