{
  "generated": "2026-07-01",
  "videos_analyzed": 385,
  "countries": 47,
  "totals": {
    "views": 291187008,
    "likes": 4411106,
    "comments": 208937
  },
  "country_attribution": "multi (b): a video is counted in every country whose search surfaced it; no per-country ranking (unreliable)",
  "top_teams": [
    {
      "team": "Brazil",
      "mentions": 4139,
      "lean": "positive",
      "positive": 2557,
      "neutral": 1308,
      "negative": 274
    },
    {
      "team": "Japan",
      "mentions": 3915,
      "lean": "positive",
      "positive": 2548,
      "neutral": 1193,
      "negative": 174
    },
    {
      "team": "Morocco",
      "mentions": 2073,
      "lean": "positive",
      "positive": 2050,
      "neutral": 23,
      "negative": 0
    },
    {
      "team": "Germany",
      "mentions": 1833,
      "lean": "negative",
      "positive": 4,
      "neutral": 89,
      "negative": 1740
    },
    {
      "team": "South Korea",
      "mentions": 1398,
      "lean": "negative",
      "positive": 3,
      "neutral": 85,
      "negative": 1310
    },
    {
      "team": "Paraguay",
      "mentions": 1332,
      "lean": "positive",
      "positive": 1301,
      "neutral": 29,
      "negative": 2
    },
    {
      "team": "Argentina",
      "mentions": 824,
      "lean": "positive",
      "positive": 423,
      "neutral": 220,
      "negative": 181
    },
    {
      "team": "Netherlands",
      "mentions": 650,
      "lean": "negative",
      "positive": 11,
      "neutral": 274,
      "negative": 365
    },
    {
      "team": "Mexico",
      "mentions": 565,
      "lean": "positive",
      "positive": 311,
      "neutral": 119,
      "negative": 135
    },
    {
      "team": "Uzbekistan",
      "mentions": 391,
      "lean": "positive",
      "positive": 294,
      "neutral": 37,
      "negative": 60
    }
  ],
  "top_videos_by_views": [
    {
      "title": "fifa world cup",
      "countries": [
        "AR",
        "AT",
        "BA",
        "BE",
        "CH",
        "CO",
        "CW",
        "CZ",
        "DE",
        "EC",
        "ES",
        "IR",
        "NL",
        "NO",
        "PA",
        "PY",
        "SE",
        "UY"
      ],
      "reach": 18,
      "narration_en": "This neutral-sentiment FIFA World Cup video trended across 18 countries including Argentina, Germany, and Spain. It reached a diverse audience speaking languages such as Spanish, German, and Dutch.",
      "narration_ja": "FIFAワールドカップに関するこの動画は、アルゼンチン、ドイツ、スペインなど18カ国でトレンド入りしました。スペイン語、ドイツ語、オランダ語などの視聴者に届いています。",
      "views": 12697836,
      "url": "https://www.youtube.com/watch?v=q0f3zSBPrA0"
    },
    {
      "title": "BRAZIL 🇧🇷 vs JAPAN 🇯🇵 | 2026 FIFA World Cup",
      "countries": [
        "AR",
        "AT",
        "BA",
        "BE",
        "CH",
        "CO",
        "CV",
        "CW",
        "CZ",
        "DE",
        "EC",
        "ES",
        "FR",
        "HR",
        "IR",
        "KR",
        "MX",
        "NL",
        "NO",
        "PA",
        "PT",
        "PY",
        "SE",
        "TR",
        "UY"
      ],
      "reach": 25,
      "narration_en": "Featuring Brazil vs Japan, this highly positive video trended in 20 countries. Comments reflect on the match intensity, celebrate Brazil's victory, and discuss both teams' performances.",
      "narration_ja": "ブラジル対日本の試合を扱ったこの動画は、20カ国でトレンド入りし、ポジティブな反響を呼んでいます。コメント欄では試合の激闘やブラジルの勝利を祝う声、両チームの健闘を称える意見が多く見られます。",
      "views": 10081884,
      "url": "https://www.youtube.com/watch?v=hJOmsa_huBk"
    },
    {
      "title": "ملخص مباراة هولندا والمغرب | دور الـ32 - كأس العالم FIFA 2026™",
      "countries": [
        "DZ",
        "EG",
        "IQ",
        "JO",
        "MA",
        "QA",
        "SA",
        "TN"
      ],
      "reach": 8,
      "narration_en": "Morocco's historic penalty shootout win against the Netherlands at the 2026 World Cup sparked immense pride across the Arab world. The video received overwhelmingly positive feedback from audiences in countries like Morocco, Egypt, and Saudi Arabia.",
      "narration_ja": "2026年W杯、モロッコがオランダをPK戦で破った歴史的勝利を振り返る動画です。モロッコ、エジプト、サウジアラビアなどの視聴者から、アラブ諸国の誇りと連帯を示す圧倒的にポジティブな反応が寄せられています。",
      "views": 7931050,
      "url": "https://www.youtube.com/watch?v=j__HOw44dYg"
    },
    {
      "title": "🥅🧤 شاهد سلسلة الركلات الترجيحية لمباراة هولندا والمغرب 🇳🇱🇲🇦",
      "countries": [
        "DZ",
        "EG",
        "IQ",
        "JO",
        "MA",
        "QA",
        "SA",
        "TN"
      ],
      "reach": 8,
      "narration_en": "This highlight reel of the Morocco vs Netherlands penalty shootout drew massive support from Arab audiences. Viewers expressed pride in the players' fighting spirit and celebrated the historic victory.",
      "narration_ja": "モロッコ対オランダ戦のPK戦ハイライトは、アラブ諸国の視聴者から大きな支持を得ました。選手たちの闘志を称え、歴史的な勝利を喜ぶ声が溢れています。",
      "views": 7295178,
      "url": "https://www.youtube.com/watch?v=9IBuC2NRihk"
    },
    {
      "title": "The Soul of Football … Pass it On! ⚽️",
      "countries": [
        "CA",
        "GB",
        "AU",
        "NZ",
        "CD",
        "CI",
        "GH",
        "HT",
        "SN",
        "US",
        "ZA",
        "FR"
      ],
      "reach": 12,
      "narration_en": "Celebrating the passion of the FIFA Fan Festival, this video trended across countries including the US, France, and South Africa. Discussions cover topics ranging from World Cup excitement to the origins of the match balls.",
      "narration_ja": "FIFAファンフェスティバルの熱気を伝えるこの動画は、アメリカ、フランス、南アフリカなどでトレンド入りしました。W杯への期待感や試合球の製造国に関する議論など、多岐にわたる話題がコメントされています。",
      "views": 6694444,
      "url": "https://www.youtube.com/watch?v=pkM09aH5Q3I"
    },
    {
      "title": "억울하니까 축구협회에 인사도 하지 말라고 안정환에게 말하는 김남일",
      "countries": [
        "KR"
      ],
      "reach": 1,
      "narration_en": "This South Korean video focuses on the friendship between Kim Nam-il and Ahn Jung-hwan amidst criticism of the Korea Football Association. The sentiment is mixed, balancing loyalty to the players with frustration toward football officials.",
      "narration_ja": "韓国サッカー協会への批判の中で、キム・ナムイルとアン・ジョンファンの友情に焦点を当てた動画です。選手への信頼と協会への不信感が入り混じった、複雑な反応が示されています。",
      "views": 5751995,
      "url": "https://www.youtube.com/watch?v=jR7wA4ZxwCo"
    },
    {
      "title": "Brazil vs Japan Fifa World Cup Match #brazil #neymar #worldcup #football #trending #viral #shorts",
      "countries": [
        "CD",
        "CI",
        "HT",
        "SN",
        "FR",
        "CA",
        "AU",
        "GB",
        "NZ",
        "GH",
        "US",
        "ZA"
      ],
      "reach": 12,
      "narration_en": "This viral short on the Brazil vs Japan match received mixed feedback across multiple countries. The conversation centers on confirming match results and reflecting on past tournament history.",
      "narration_ja": "ブラジル対日本の試合を扱ったこのショート動画は、各国の視聴者から様々な反応を得ました。試合結果の確認や、過去の大会の歴史を振り返るような内容が議論されています。",
      "views": 5596865,
      "url": "https://www.youtube.com/watch?v=Q7dNpnCLq4w"
    },
    {
      "title": "June 28 Matchday Recap | #FIFAWorldCup @aramco",
      "countries": [
        "AU",
        "CA",
        "CD",
        "GB",
        "GH",
        "HT",
        "US",
        "NZ",
        "SN",
        "ZA",
        "CI",
        "FR"
      ],
      "reach": 12,
      "narration_en": "Covering the June 28 World Cup matchday, this recap video trended globally. Viewers shared excitement for goals while expressing mixed sentiments regarding specific match results.",
      "narration_ja": "6月28日のW杯試合結果をまとめた動画が世界中でトレンド入りしました。ゴールシーンへの興奮や、特定の試合結果に対する様々な感想が寄せられています。",
      "views": 5231484,
      "url": "https://www.youtube.com/watch?v=d2X-qKsRk10"
    },
    {
      "title": "Casemiro scores the equalizer for Brazil against Japan. #FIFAWorldCupOnYT",
      "countries": [
        "AU",
        "CA",
        "GB",
        "NZ",
        "GH",
        "ZA",
        "CD",
        "CI",
        "HT",
        "SN",
        "US",
        "FR",
        "CH",
        "AT",
        "DE"
      ],
      "reach": 15,
      "narration_en": "This video featuring Casemiro’s goal in the Brazil vs Japan match sparked debates over refereeing and tactical performances. It resonated with an international audience across 15 countries.",
      "narration_ja": "ブラジル対日本戦でのカゼミロのゴールを収めたこの動画は、審判の判定や戦術をめぐって議論を呼びました。15カ国の国際的な視聴者に視聴されています。",
      "views": 4953537,
      "url": "https://www.youtube.com/watch?v=_iu7diQa_Is"
    },
    {
      "title": "マルキーニョス うざいって！2026 FIFA ワールドカップ 日本 vs ブラジル 【本田圭佑解説】",
      "countries": [
        "JP"
      ],
      "reach": 1,
      "narration_en": "Keisuke Honda’s commentary on Japan’s loss to Brazil gained significant popularity in Japan. The overall sentiment is positive, with fans expressing gratitude for the national team’s effort despite the defeat.",
      "narration_ja": "日本対ブラジル戦における本田圭佑の解説動画が日本で高い人気を博しました。試合には敗れたものの、日本代表の健闘を称える感謝のコメントが多く寄せられています。",
      "views": 4438176,
      "url": "https://www.youtube.com/watch?v=WIvVn-UPl98"
    }
  ],
  "top_videos_by_reach": [
    {
      "title": "Highlights | South Africa 0-1 Canada | FIFA World Cup 2026™",
      "countries": [
        "UZ",
        "HR",
        "MX",
        "JP",
        "BR",
        "AU",
        "GB",
        "GH",
        "CA",
        "NZ",
        "US",
        "ZA",
        "CD",
        "HT",
        "SN",
        "CI",
        "PT",
        "FR",
        "CV",
        "TR",
        "IR",
        "BA",
        "CH",
        "CW",
        "PY",
        "BE",
        "KR",
        "NL",
        "NO",
        "SE",
        "AR",
        "AT",
        "CO",
        "CZ",
        "PA",
        "DE",
        "EC",
        "UY",
        "ES"
      ],
      "reach": 39,
      "narration_en": "",
      "narration_ja": "",
      "views": 387870,
      "url": "https://www.youtube.com/watch?v=uv-FSqzHXAo"
    },
    {
      "title": "Highlights | Jordan 1-3 Argentina | FIFA World Cup 2026™",
      "countries": [
        "BR",
        "AU",
        "CA",
        "GB",
        "NZ",
        "GH",
        "US",
        "ZA",
        "CD",
        "CI",
        "HT",
        "SN",
        "CV",
        "FR",
        "PT",
        "PY",
        "AR",
        "CH",
        "CO",
        "PA",
        "BA",
        "BE",
        "CW",
        "KR",
        "CZ",
        "IR",
        "AT",
        "EC",
        "ES",
        "NL",
        "NO",
        "TR",
        "UY",
        "DE",
        "SE"
      ],
      "reach": 35,
      "narration_en": "",
      "narration_ja": "",
      "views": 1830421,
      "url": "https://www.youtube.com/watch?v=M6mpXtMm93M"
    },
    {
      "title": "Highlights | Algeria 3-3 Austria | FIFA World Cup 2026™",
      "countries": [
        "AU",
        "BR",
        "CA",
        "NZ",
        "CD",
        "GB",
        "GH",
        "HT",
        "SN",
        "ZA",
        "CI",
        "FR",
        "PT",
        "KR",
        "CH",
        "IR",
        "TR",
        "AT",
        "BA",
        "CV",
        "CW",
        "PY",
        "AR",
        "BE",
        "CO",
        "DE",
        "NL",
        "NO",
        "PA",
        "SE",
        "CZ",
        "EC",
        "UY",
        "ES"
      ],
      "reach": 34,
      "narration_en": "",
      "narration_ja": "",
      "views": 610114,
      "url": "https://www.youtube.com/watch?v=5Mvh0mqY8ik"
    },
    {
      "title": "Paraguay Eliminate Germany On Penalties | FIFA World Cup 2026™",
      "countries": [
        "BR",
        "AU",
        "CA",
        "GB",
        "GH",
        "CD",
        "HT",
        "NZ",
        "ZA",
        "SN",
        "CI",
        "PT",
        "FR",
        "TR",
        "CV",
        "IR",
        "BA",
        "CH",
        "CW",
        "BE",
        "KR",
        "NL",
        "NO",
        "PY",
        "SE",
        "AR",
        "AT",
        "CO",
        "CZ",
        "PA",
        "DE",
        "EC",
        "UY",
        "ES"
      ],
      "reach": 34,
      "narration_en": "",
      "narration_ja": "",
      "views": 473814,
      "url": "https://www.youtube.com/watch?v=lq3o-vf5o40"
    },
    {
      "title": "Highlights | Colombia 0-0 Portugal | FIFA World Cup 2026™",
      "countries": [
        "BR",
        "CA",
        "AU",
        "GB",
        "NZ",
        "CD",
        "HT",
        "CI",
        "FR",
        "GH",
        "SN",
        "PT",
        "ZA",
        "BA",
        "AR",
        "BE",
        "CH",
        "CO",
        "CW",
        "IR",
        "PA",
        "PY",
        "CZ",
        "NL",
        "NO",
        "CV",
        "SE",
        "AT",
        "TR",
        "DE",
        "EC",
        "ES",
        "UY"
      ],
      "reach": 33,
      "narration_en": "",
      "narration_ja": "",
      "views": 863364,
      "url": "https://www.youtube.com/watch?v=QhI0dUq1FKY"
    },
    {
      "title": "Netherlands 🆚 Morocco #FIFAWorldCupOnYT",
      "countries": [
        "BR",
        "MX",
        "UZ",
        "JP",
        "AU",
        "CA",
        "GB",
        "NZ",
        "GH",
        "ZA",
        "CD",
        "CI",
        "CV",
        "HT",
        "PT",
        "PY",
        "SN",
        "US",
        "AR",
        "CO",
        "FR",
        "PA",
        "BE",
        "CH",
        "CW",
        "KR",
        "EC",
        "ES",
        "TR",
        "UY",
        "AT",
        "DE"
      ],
      "reach": 32,
      "narration_en": "",
      "narration_ja": "",
      "views": 3203139,
      "url": "https://www.youtube.com/watch?v=MPXsMR5m5Io"
    },
    {
      "title": "Highlights | Congo DR 3-1 Uzbekistan | FIFA World Cup 2026™",
      "countries": [
        "BR",
        "AU",
        "GH",
        "NZ",
        "ZA",
        "CD",
        "HT",
        "SN",
        "CI",
        "FR",
        "PT",
        "CV",
        "TR",
        "IR",
        "BA",
        "CH",
        "CW",
        "PY",
        "BE",
        "KR",
        "NL",
        "NO",
        "SE",
        "AR",
        "AT",
        "CO",
        "CZ",
        "PA",
        "DE",
        "EC",
        "UY",
        "ES"
      ],
      "reach": 32,
      "narration_en": "",
      "narration_ja": "",
      "views": 405891,
      "url": "https://www.youtube.com/watch?v=_effg5dZWZc"
    },
    {
      "title": "Germany 🆚 Paraguay #FIFAWorldCupOnYT #shorts #worldcup",
      "countries": [
        "UZ",
        "JP",
        "MX",
        "AU",
        "CA",
        "GB",
        "NZ",
        "GH",
        "ZA",
        "CD",
        "CI",
        "HT",
        "PY",
        "SN",
        "US",
        "AR",
        "CO",
        "FR",
        "PA",
        "CH",
        "CZ",
        "EC",
        "ES",
        "TR",
        "UY",
        "AT",
        "DE"
      ],
      "reach": 27,
      "narration_en": "",
      "narration_ja": "",
      "views": 2413421,
      "url": "https://www.youtube.com/watch?v=n73HW9dr5E0"
    },
    {
      "title": "Brazil vs Japan |  World Cup 2026 | Video Game Simulation Match",
      "countries": [
        "CD",
        "HT",
        "SN",
        "CI",
        "FR",
        "PT",
        "KR",
        "CH",
        "IR",
        "TR",
        "AT",
        "BA",
        "CV",
        "CW",
        "PY",
        "AR",
        "BE",
        "CO",
        "DE",
        "NL",
        "NO",
        "PA",
        "SE",
        "CZ",
        "EC",
        "UY",
        "ES"
      ],
      "reach": 27,
      "narration_en": "",
      "narration_ja": "",
      "views": 573574,
      "url": "https://www.youtube.com/watch?v=GxCJJySfxi4"
    },
    {
      "title": "HIGHLIGHTS: Netherlands vs Morocco | FIFA World Cup 2026™ | 30/06/2026",
      "countries": [
        "CD",
        "CI",
        "HT",
        "SN",
        "CV",
        "FR",
        "PT",
        "TR",
        "AR",
        "AT",
        "BA",
        "BE",
        "CH",
        "CO",
        "CW",
        "CZ",
        "DE",
        "EC",
        "ES",
        "IR",
        "NL",
        "NO",
        "PA",
        "PY",
        "SE",
        "UY"
      ],
      "reach": 26,
      "narration_en": "",
      "narration_ja": "",
      "views": 4250123,
      "url": "https://www.youtube.com/watch?v=z9umI2sq4ZE"
    }
  ],
  "sentiment_avg": {
    "positive": 49.249350649350646,
    "negative": 26.4025974025974,
    "neutral": 24.34805194805195
  },
  "comments_analyzed": 25138,
  "top_positive_themes": [
    {
      "theme_en": "Support for Brazil national team",
      "theme_ja": "ブラジル代表への応援",
      "mentions": 331
    },
    {
      "theme_en": "Congratulations on Morocco's victory",
      "theme_ja": "モロッコ代表の勝利への祝福",
      "mentions": 310
    },
    {
      "theme_en": "Historic victory for Paraguay",
      "theme_ja": "パラグアイの歴史的勝利",
      "mentions": 195
    },
    {
      "theme_en": "Praise for Japan's performance",
      "theme_ja": "日本の戦いぶりへの称賛",
      "mentions": 176
    },
    {
      "theme_en": "Praise for Paraguay's historic victory",
      "theme_ja": "パラグアイの歴史的勝利への称賛",
      "mentions": 150
    },
    {
      "theme_en": "Paraguay's historic victory",
      "theme_ja": "パラグアイの歴史的勝利",
      "mentions": 123
    },
    {
      "theme_en": "Hopes for winning the World Cup",
      "theme_ja": "ワールドカップ優勝への期待",
      "mentions": 120
    },
    {
      "theme_en": "Zion Suzuki's super saves",
      "theme_ja": "鈴木彩艶のスーパーセーブ",
      "mentions": 120
    }
  ],
  "top_negative_themes": [
    {
      "theme_en": "Distrust towards the Korea Football Association",
      "theme_ja": "サッカー協会（KFA）への不信感",
      "mentions": 110
    },
    {
      "theme_en": "Lack of respect for the opponent",
      "theme_ja": "相手へのリスペクト不足",
      "mentions": 85
    },
    {
      "theme_en": "Germany's poor performance and elimination",
      "theme_ja": "ドイツ代表の不振と敗退",
      "mentions": 75
    },
    {
      "theme_en": "Criticism and resignation demands for Hong Myung-bo",
      "theme_ja": "洪明甫監督への批判と解任要求",
      "mentions": 75
    },
    {
      "theme_en": "Germany's recent decline",
      "theme_ja": "ドイツ代表の近年の低迷",
      "mentions": 75
    },
    {
      "theme_en": "Sadness over retirement",
      "theme_ja": "引退に対する悲しみ",
      "mentions": 75
    },
    {
      "theme_en": "Criticism of national character",
      "theme_ja": "国民性への批判",
      "mentions": 70
    },
    {
      "theme_en": "Frustration over the defeat",
      "theme_ja": "敗戦による悔しさ",
      "mentions": 65
    }
  ]
}